mvedemo/__init.py
mvedemo/compute_camspairCC.py
mvedemo/compute_sfm.py
mvedemo/key_exact.py
mvedemo/utils.py
mvedemo/videotoply.py
mvedemo/videotoply_gui.py
mvedemo/vis_gui.py
mvedemo/build/lib/datasets/__init__.py
mvedemo/build/lib/datasets/custom.py
mvedemo/build/lib/datasets/data_io.py
mvedemo/build/lib/datasets/dtu_yao.py
mvedemo/build/lib/datasets/dtu_yao_eval.py
mvedemo/build/lib/models/__init__.py
mvedemo/build/lib/models/module.py
mvedemo/build/lib/models/net.py
mvedemo/build/lib/models/patchmatch.py
mvedemo/datasets/__init__.py
mvedemo/datasets/custom.py
mvedemo/datasets/data_io.py
mvedemo/datasets/dtu_yao.py
mvedemo/datasets/dtu_yao_eval.py
mvedemo/models/__init__.py
mvedemo/models/module.py
mvedemo/models/net.py
mvedemo/models/patchmatch.py
mvedemo/venv/birdas.py
mvedemo/venv/Scripts/activate_this.py
mve2-0.0.2.dist-info/METADATA
mve2-0.0.2.dist-info/WHEEL
mve2-0.0.2.dist-info/top_level.txt
mve2-0.0.2.dist-info/RECORD
