Metadata-Version: 2.1
Name: mve2
Version: 0.0.2
Summary: demo
Author-email: 1060388271@qq.com
License: apache 3.0
